nagini3d_napari/__init__.py
nagini3d_napari/_version.py
nagini3d_napari/_widget.py
nagini3d_napari/napari.yaml
nagini3d_napari-0.1.0.dist-info/licenses/LICENSE
nagini3d_napari-0.1.0.dist-info/METADATA
nagini3d_napari-0.1.0.dist-info/WHEEL
nagini3d_napari-0.1.0.dist-info/entry_points.txt
nagini3d_napari-0.1.0.dist-info/top_level.txt
nagini3d_napari-0.1.0.dist-info/RECORD
