Metadata-Version: 2.4
Name: nagini3d-napari
Version: 0.1.0
Summary: A simple plugin that implements Nagini3D inference tools 3D biological segmentation.
Author: Quentin RAPILLY
Author-email: quentin.rapilly.ia@gmail.com
License: 
Project-URL: Bug Tracker, https://github.com/QuentinRapilly/nagini3d-napari/issues
Project-URL: Documentation, https://github.com/QuentinRapilly/nagini3d-napari#README.md
Project-URL: Source Code, https://github.com/QuentinRapilly/nagini3d-napari
Project-URL: User Support, https://github.com/QuentinRapilly/nagini3d-napari/issues
Classifier: Development Status :: 2 - Pre-Alpha
Classifier: Framework :: napari
Classifier: Intended Audience :: Developers
Classifier: License :: OSI Approved :: GNU General Public License v3 (GPLv3)
Classifier: Operating System :: OS Independent
Classifier: Programming Language :: Python
Classifier: Programming Language :: Python :: 3
Classifier: Programming Language :: Python :: 3 :: Only
Classifier: Programming Language :: Python :: 3.10
Classifier: Programming Language :: Python :: 3.11
Classifier: Programming Language :: Python :: 3.12
Classifier: Programming Language :: Python :: 3.13
Classifier: Topic :: Scientific/Engineering :: Image Processing
Requires-Python: >=3.10
License-File: LICENSE
Requires-Dist: numpy
Requires-Dist: magicgui
Requires-Dist: qtpy
Requires-Dist: scikit-image
Requires-Dist: scikit-learn
Requires-Dist: torch==2.1.0
Requires-Dist: torchvision==0.16.0
Requires-Dist: nagini3d==0.2.2
Provides-Extra: all
Requires-Dist: napari[all]; extra == "all"
Dynamic: license-file
